btw_i_use_arch/__init__.py
btw_i_use_arch/btw_i_use_arch.py
btw_i_use_arch/cli.py
btw_i_use_arch/countdown.py
btw_i_use_arch/downloader.py
btw_i_use_arch/warden.py
btw_i_use_arch-0.2.0.dist-info/AUTHORS.rst
btw_i_use_arch-0.2.0.dist-info/LICENSE
btw_i_use_arch-0.2.0.dist-info/METADATA
btw_i_use_arch-0.2.0.dist-info/WHEEL
btw_i_use_arch-0.2.0.dist-info/entry_points.txt
btw_i_use_arch-0.2.0.dist-info/top_level.txt
btw_i_use_arch-0.2.0.dist-info/RECORD
