Metadata-Version: 2.1
Name: btw-i-use-arch
Version: 0.2.0
Summary: Helper CLI for installing packages and setting up Linux components
Home-page: https://github.com/kellerjustin/btw_i_use_arch
Author: Justin Keller
Author-email: kellerjustin@protonmail.com
License: MIT license
Keywords: btw_i_use_arch
Classifier: Development Status :: 2 - Pre-Alpha
Classifier: Intended Audience :: Developers
Classifier: License :: OSI Approved :: MIT License
Classifier: Natural Language :: English
Classifier: Programming Language :: Python :: 3
Classifier: Programming Language :: Python :: 3.5
Classifier: Programming Language :: Python :: 3.6
Classifier: Programming Language :: Python :: 3.7
Classifier: Programming Language :: Python :: 3.8
Requires-Python: >=3.5
License-File: LICENSE
License-File: AUTHORS.rst
Requires-Dist: Click >=7.0
Requires-Dist: simple-term-menu
Requires-Dist: keyring >=23.5.1
Requires-Dist: requests >=2.26.0
Requires-Dist: simple-term-menu >=1.0.1
Requires-Dist: appdirs >=1.4.4
